[
  [
    {
      "name": "",
      "room": [
        "104",
        "107",
        "108",
        "113",
        "115",
        "116",
        "A101",
        "A102",
        "A103",
        "A104",
        "A105",
        "A107",
        "A110",
        "A211",
        "A214",
        "A330",
        "A424",
        "A431",
        "A514",
        "A606",
        "A607",
        "A608",
        "A610",
        "A611",
        "A612",
        "A615",
        "A618",
        "B102",
        "B104",
        "B105",
        "B107",
        "N100",
        "N101",
        "N103",
        "N105",
        "N107",
        "N109",
        "N111",
        "N201",
        "N301",
        "N303",
        "N305",
        "N307",
        "N309",
        "N311",
        "S102",
        "S104",
        "S106",
        "S108",
        "S110",
        "S112",
        "S114",
        "S116",
        "S118",
        "S202",
        "S204",
        "S206",
        "S208",
        "S210",
        "S302",
        "S304",
        "S306",
        "S308",
        "S310",
        "S312",
        "S314"
      ]
    },
    {
      "name": "B",
      "room": [
        "101",
        "103",
        "104",
        "105",
        "106",
        "107",
        "108",
        "109",
        "201",
        "202",
        "203",
        "204",
        "205",
        "206",
        "207",
        "208",
        "209",
        "210",
        "211",
        "301",
        "302",
        "303",
        "304",
        "305",
        "306",
        "307",
        "308",
        "309",
        "310",
        "311",
        "312",
        "313",
        "401",
        "402",
        "403",
        "404",
        "405",
        "406",
        "407",
        "408",
        "410",
        "411",
        "412",
        "413",
        "502",
        "504",
        "519",
        "521",
        "523",
        "525"
      ]
    },
    {
      "name": "北四阶",
      "room": [
        "北四阶"
      ]
    },
    {
      "name": "测试中心",
      "room": [
        "104",
        "105"
      ]
    },
    {
      "name": "车间",
      "room": [
        "1",
        "2"
      ]
    },
    {
      "name": "锻压楼",
      "room": [
        "101",
        "102",
        "103",
        "104",
        "105",
        "106",
        "107",
        "210"
      ]
    },
    {
      "name": "二教楼",
      "room": [
        "101",
        "102",
        "103",
        "104",
        "105",
        "106",
        "107",
        "108",
        "109",
        "110",
        "111",
        "113",
        "114",
        "115",
        "116",
        "117",
        "118",
        "119",
        "120",
        "121",
        "123",
        "201",
        "208",
        "210",
        "212",
        "216",
        "217",
        "219",
        "220",
        "221",
        "222",
        "223",
        "224",
        "225",
        "314",
        "319",
        "405"
      ]
    },
    {
      "name": "法学附",
      "room": [
        "202"
      ]
    },
    {
      "name": "封样室",
      "room": [
        "封样室"
      ]
    },
    {
      "name": "工科楼",
      "room": [
        "S101",
        "S102",
        "S110",
        "S110",
        "S111",
        "S201",
        "S202",
        "S203",
        "S204",
        "S206",
        "S207",
        "S208",
        "S210",
        "S211",
        "S212",
        "S213",
        "S215",
        "S218",
        "S219",
        "S220",
        "S302",
        "S308",
        "S310",
        "S402",
        "S403",
        "S409",
        "S420",
        "N504",
        "N601",
        "N602",
        "N603",
        "S502",
        "S503",
        "S513",
        "S514",
        "S602",
        "S609",
        "S610",
        "S611",
        "S612"
      ]
    },
    {
      "name": "工科楼阶梯",
      "room": [
        "工科楼阶梯"
      ]
    },
    {
      "name": "工科楼南楼",
      "room": [
        "103",
        "104",
        "105",
        "106",
        "107",
        "108",
        "109",
        "209",
        "214",
        "216",
        "217"
      ]
    },
    {
      "name": "焊接楼",
      "room": [
        "106",
        "101",
        "104",
        "105",
        "109",
        "111",
        "112",
        "113",
        "114",
        "115",
        "116",
        "117",
        "118",
        "119",
        "206",
        "208",
        "210",
        "211",
        "212",
        "213",
        "214",
        "215",
        "216",
        "303",
        "303",
        "305",
        "307",
        "310",
        "311",
        "311",
        "312",
        "313",
        "314",
        "316"
      ]
    },
    {
      "name": "化机楼",
      "room": [
        "101",
        "102",
        "103",
        "104",
        "105",
        "106",
        "107",
        "108",
        "109",
        "111",
        "112",
        "201",
        "204",
        "207",
        "209",
        "210",
        "212",
        "214",
        "215"
      ]
    },
    {
      "name": "环工实验室",
      "room": [
        "101",
        "105",
        "113",
        "115",
        "206",
        "213",
        "303",
        "310",
        "323"
      ]
    },
    {
      "name": "机械楼",
      "room": [
        "204",
        "115",
        "116",
        "215",
        "319",
        "320",
        "321",
        "502",
        "503",
        "505",
        "506",
        "507",
        "508",
        "511",
        "513",
        "515",
        "517",
        "601",
        "602",
        "603",
        "604",
        "605",
        "606",
        "608",
        "609",
        "610",
        "611",
        "612",
        "614",
        "615",
        "616",
        "617"
      ]
    },
    {
      "name": "机制大厅",
      "room": [
        "机制大厅"
      ]
    },
    {
      "name": "机制厅",
      "room": [
        "101",
        "102",
        "103",
        "104",
        "201",
        "204"
      ]
    },
    {
      "name": "计算中心",
      "room": [
        "B202"
      ]
    },
    {
      "name": "经管楼",
      "room": [
        "617",
        "301",
        "302",
        "306",
        "406"
      ]
    },
    {
      "name": "联建",
      "room": [
        "D201"
      ]
    },
    {
      "name": "模具大厅",
      "room": [
        "模具大厅"
      ]
    },
    {
      "name": "模具厅",
      "room": [
        "101",
        "102"
      ]
    },
    {
      "name": "南山阶梯",
      "room": [
        "南山三阶梯"
      ]
    },
    {
      "name": "三教宿",
      "room": [
        "202"
      ]
    },
    {
      "name": "生食工楼",
      "room": [
        "222"
      ]
    },
    {
      "name": "实验楼",
      "room": [
        "309"
      ]
    },
    {
      "name": "数学院报告厅",
      "room": [
        "数学院报告厅"
      ]
    },
    {
      "name": "四教区",
      "room": [
        "1101",
        "1103",
        "1104",
        "1105",
        "1106",
        "1107",
        "1108",
        "1109",
        "1112",
        "1203",
        "1204",
        "1205",
        "1206",
        "1207",
        "1208",
        "1209",
        "1210",
        "1304",
        "1305",
        "1306",
        "1307",
        "1308",
        "1309",
        "1310",
        "1403",
        "1404",
        "1405",
        "1406",
        "1407",
        "1408",
        "1409",
        "1410",
        "1503",
        "1504",
        "1505",
        "1506",
        "1507",
        "1508",
        "1509",
        "1510",
        "1512",
        "1601",
        "1613",
        "2201",
        "2202",
        "2203",
        "2204",
        "2205",
        "2301",
        "2302",
        "2303",
        "2304",
        "2305",
        "2401",
        "2402",
        "2403",
        "2404",
        "2405",
        "2501",
        "2502",
        "2503",
        "2504",
        "2505"
      ]
    },
    {
      "name": "四教区图书馆",
      "room": [
        "203",
        "303",
        "403"
      ]
    },
    {
      "name": "体育馆",
      "room": [
        "210"
      ]
    },
    {
      "name": "土木楼",
      "room": [
        "A426",
        "A518",
        "A601",
        "A604",
        "A605"
      ]
    },
    {
      "name": "外语楼",
      "room": [
        "105",
        "106",
        "220",
        "316",
        "401"
      ]
    },
    {
      "name": "文科楼",
      "room": [
        "102",
        "103",
        "106",
        "107",
        "206",
        "207",
        "301",
        "302",
        "303",
        "304",
        "305",
        "306",
        "307",
        "308",
        "401",
        "402",
        "403",
        "1楼",
        "1楼",
        "2楼",
        "405",
        "505"
      ]
    },
    {
      "name": "小二楼二楼",
      "room": [
        "小二楼二楼"
      ]
    },
    {
      "name": "小二楼一楼",
      "room": [
        "小二楼一楼"
      ]
    },
    {
      "name": "信息楼",
      "room": [
        "103",
        "104",
        "105",
        "106",
        "408",
        "409",
        "201",
        "301",
        "601",
        "603",
        "609"
      ]
    },
    {
      "name": "信息楼605",
      "room": [
        "1",
        "2"
      ]
    },
    {
      "name": "兴教楼",
      "room": [
        "B202",
        "B302",
        "B304",
        "B310",
        "B402",
        "B403",
        "B408",
        "B409",
        "C103",
        "C303"
      ]
    },
    {
      "name": "兴湘教学楼",
      "room": [
        "A101",
        "A102",
        "A103",
        "A104",
        "A105",
        "A106",
        "A201",
        "A202",
        "A203",
        "A204",
        "A205",
        "A206",
        "A207",
        "A208",
        "A301",
        "A302",
        "A303",
        "A304",
        "A305",
        "A306",
        "A307",
        "A308",
        "A309",
        "A401",
        "A402",
        "A410",
        "A415"
      ]
    },
    {
      "name": "兴湘学院三教",
      "room": [
        "101",
        "102",
        "104",
        "202",
        "203",
        "204",
        "205",
        "302",
        "303",
        "304",
        "305",
        "402",
        "403",
        "404",
        "405",
        "501",
        "502"
      ]
    },
    {
      "name": "一教楼",
      "room": [
        "101",
        "103",
        "107",
        "115",
        "117",
        "119",
        "201",
        "202",
        "203",
        "204",
        "205",
        "206",
        "207",
        "208",
        "212",
        "213",
        "214",
        "215",
        "216",
        "217",
        "219",
        "301",
        "302",
        "303",
        "304",
        "305",
        "306",
        "307",
        "308",
        "312",
        "313",
        "314",
        "315",
        "316",
        "317",
        "401",
        "402",
        "414",
        "415",
        "416",
        "417",
        "418"
      ]
    },
    {
      "name": "逸夫楼",
      "room": [
        "401"
      ]
    }
  ],
  [
    {
      "name": "",
      "room": [
        "104",
        "107",
        "108",
        "113",
        "115",
        "116",
        "A101",
        "A102",
        "A103",
        "A104",
        "A105",
        "A107",
        "A110",
        "A211",
        "A214",
        "A330",
        "A424",
        "A431",
        "A514",
        "A606",
        "A607",
        "A608",
        "A610",
        "A611",
        "A612",
        "A615",
        "A618",
        "B102",
        "B104",
        "B105",
        "B107",
        "N100",
        "N101",
        "N103",
        "N105",
        "N107",
        "N109",
        "N111",
        "N201",
        "N301",
        "N303",
        "N305",
        "N307",
        "N309",
        "N311",
        "S102",
        "S104",
        "S106",
        "S108",
        "S110",
        "S112",
        "S114",
        "S116",
        "S118",
        "S202",
        "S204",
        "S206",
        "S208",
        "S210",
        "S302",
        "S304",
        "S306",
        "S308",
        "S310",
        "S312",
        "S314"
      ]
    },
    {
      "name": "B",
      "room": [
        "101",
        "103",
        "104",
        "105",
        "106",
        "107",
        "108",
        "109",
        "201",
        "202",
        "203",
        "204",
        "205",
        "206",
        "207",
        "208",
        "209",
        "210",
        "211",
        "301",
        "302",
        "303",
        "304",
        "305",
        "306",
        "307",
        "308",
        "309",
        "310",
        "311",
        "312",
        "313",
        "401",
        "402",
        "403",
        "404",
        "405",
        "406",
        "407",
        "408",
        "410",
        "411",
        "412",
        "413",
        "502",
        "504",
        "519",
        "521",
        "523",
        "525"
      ]
    },
    {
      "name": "北四阶",
      "room": [
        "北四阶"
      ]
    },
    {
      "name": "测试中心",
      "room": [
        "104",
        "105"
      ]
    },
    {
      "name": "车间",
      "room": [
        "1",
        "2"
      ]
    },
    {
      "name": "锻压楼",
      "room": [
        "101",
        "102",
        "103",
        "104",
        "105",
        "106",
        "107",
        "210"
      ]
    },
    {
      "name": "二教楼",
      "room": [
        "101",
        "102",
        "103",
        "104",
        "105",
        "106",
        "107",
        "108",
        "109",
        "110",
        "111",
        "113",
        "114",
        "115",
        "116",
        "117",
        "118",
        "119",
        "120",
        "121",
        "123",
        "201",
        "208",
        "210",
        "212",
        "216",
        "217",
        "219",
        "220",
        "221",
        "222",
        "223",
        "224",
        "225",
        "314",
        "319",
        "405"
      ]
    },
    {
      "name": "封样室",
      "room": [
        "封样室"
      ]
    },
    {
      "name": "工科楼",
      "room": [
        "S101",
        "S102",
        "S110",
        "S110",
        "S111",
        "S201",
        "S202",
        "S203",
        "S204",
        "S206",
        "S207",
        "S208",
        "S210",
        "S211",
        "S212",
        "S213",
        "S215",
        "S218",
        "S219",
        "S220",
        "S302",
        "S308",
        "S310",
        "S402",
        "S403",
        "S409",
        "S420",
        "N504",
        "N601",
        "N602",
        "N603",
        "S502",
        "S503",
        "S513",
        "S514",
        "S602",
        "S609",
        "S610",
        "S611",
        "S612"
      ]
    },
    {
      "name": "工科楼阶梯",
      "room": [
        "工科楼阶梯"
      ]
    },
    {
      "name": "工科楼南楼",
      "room": [
        "103",
        "104",
        "105",
        "106",
        "107",
        "108",
        "109",
        "209",
        "214",
        "216",
        "217"
      ]
    },
    {
      "name": "焊接楼",
      "room": [
        "106",
        "101",
        "104",
        "105",
        "109",
        "111",
        "112",
        "113",
        "114",
        "115",
        "116",
        "117",
        "118",
        "119",
        "206",
        "208",
        "210",
        "211",
        "212",
        "213",
        "214",
        "215",
        "216",
        "303",
        "303",
        "305",
        "307",
        "310",
        "311",
        "311",
        "312",
        "313",
        "314",
        "316"
      ]
    },
    {
      "name": "化机楼",
      "room": [
        "101",
        "102",
        "103",
        "104",
        "105",
        "106",
        "107",
        "108",
        "109",
        "111",
        "112",
        "201",
        "204",
        "207",
        "209",
        "210",
        "212",
        "214",
        "215"
      ]
    },
    {
      "name": "环工实验室",
      "room": [
        "101",
        "105",
        "113",
        "115",
        "206",
        "213",
        "303",
        "310",
        "323"
      ]
    },
    {
      "name": "机械楼",
      "room": [
        "204",
        "115",
        "116",
        "215",
        "319",
        "320",
        "321",
        "502",
        "503",
        "505",
        "506",
        "507",
        "508",
        "511",
        "513",
        "515",
        "517",
        "601",
        "602",
        "603",
        "604",
        "605",
        "606",
        "608",
        "609",
        "610",
        "611",
        "612",
        "614",
        "615",
        "616",
        "617"
      ]
    },
    {
      "name": "机制大厅",
      "room": [
        "机制大厅"
      ]
    },
    {
      "name": "机制厅",
      "room": [
        "101",
        "102",
        "103",
        "104",
        "201",
        "204"
      ]
    },
    {
      "name": "计算中心",
      "room": [
        "B202"
      ]
    },
    {
      "name": "经管楼",
      "room": [
        "617",
        "301",
        "302",
        "306",
        "406"
      ]
    },
    {
      "name": "联建",
      "room": [
        "D201"
      ]
    },
    {
      "name": "模具大厅",
      "room": [
        "模具大厅"
      ]
    },
    {
      "name": "模具厅",
      "room": [
        "101",
        "102"
      ]
    },
    {
      "name": "三教宿",
      "room": [
        "202"
      ]
    },
    {
      "name": "生食工楼",
      "room": [
        "222"
      ]
    },
    {
      "name": "实验楼",
      "room": [
        "309"
      ]
    },
    {
      "name": "数学院报告厅",
      "room": [
        "数学院报告厅"
      ]
    },
    {
      "name": "四教区",
      "room": [
        "1101",
        "1103",
        "1104",
        "1105",
        "1106",
        "1107",
        "1108",
        "1109",
        "1112",
        "1203",
        "1204",
        "1205",
        "1206",
        "1207",
        "1208",
        "1209",
        "1210",
        "1304",
        "1305",
        "1306",
        "1307",
        "1308",
        "1309",
        "1310",
        "1403",
        "1404",
        "1405",
        "1406",
        "1407",
        "1408",
        "1409",
        "1410",
        "1503",
        "1504",
        "1505",
        "1506",
        "1507",
        "1508",
        "1509",
        "1510",
        "1512",
        "1601",
        "1613",
        "2201",
        "2202",
        "2203",
        "2204",
        "2205",
        "2301",
        "2302",
        "2303",
        "2304",
        "2305",
        "2401",
        "2402",
        "2403",
        "2404",
        "2405",
        "2501",
        "2502",
        "2503",
        "2504",
        "2505"
      ]
    },
    {
      "name": "四教区图书馆",
      "room": [
        "303",
        "403"
      ]
    },
    {
      "name": "体育馆",
      "room": [
        "210"
      ]
    },
    {
      "name": "图书馆文献检索室",
      "room": [
        "图书馆文献检索室"
      ]
    },
    {
      "name": "土木楼",
      "room": [
        "A426",
        "A518",
        "A601",
        "A603",
        "A604",
        "A605"
      ]
    },
    {
      "name": "外语楼",
      "room": [
        "105",
        "106",
        "401"
      ]
    },
    {
      "name": "文科楼",
      "room": [
        "102",
        "103",
        "106",
        "107",
        "206",
        "207",
        "208",
        "301",
        "302",
        "303",
        "304",
        "305",
        "306",
        "307",
        "308",
        "401",
        "402",
        "403",
        "1楼",
        "1楼",
        "2楼",
        "405",
        "505"
      ]
    },
    {
      "name": "小二楼二楼",
      "room": [
        "小二楼二楼"
      ]
    },
    {
      "name": "小二楼一楼",
      "room": [
        "小二楼一楼"
      ]
    },
    {
      "name": "信息楼",
      "room": [
        "103",
        "104",
        "105",
        "106",
        "408",
        "409",
        "201",
        "301",
        "601",
        "603",
        "609"
      ]
    },
    {
      "name": "信息楼605",
      "room": [
        "1",
        "2"
      ]
    },
    {
      "name": "兴教楼",
      "room": [
        "B102",
        "B202",
        "B302",
        "B310",
        "B402",
        "B404",
        "B408",
        "B409",
        "C104"
      ]
    },
    {
      "name": "兴湘教学楼",
      "room": [
        "A101",
        "A102",
        "A103",
        "A104",
        "A105",
        "A106",
        "A201",
        "A202",
        "A203",
        "A204",
        "A205",
        "A206",
        "A207",
        "A208",
        "A301",
        "A302",
        "A303",
        "A304",
        "A305",
        "A306",
        "A307",
        "A308",
        "A309",
        "A401",
        "A402",
        "A410",
        "A415"
      ]
    },
    {
      "name": "兴湘学院三教",
      "room": [
        "101",
        "104",
        "203",
        "204",
        "303",
        "304",
        "402",
        "403",
        "404",
        "405",
        "502"
      ]
    },
    {
      "name": "一教楼",
      "room": [
        "103",
        "105",
        "117",
        "201",
        "203",
        "204",
        "205",
        "207",
        "208",
        "212",
        "213",
        "214",
        "215",
        "216",
        "217",
        "301",
        "302",
        "303",
        "304",
        "305",
        "306",
        "307",
        "308",
        "312",
        "313",
        "314",
        "315",
        "316",
        "317",
        "401",
        "402",
        "414",
        "415",
        "416",
        "417",
        "418"
      ]
    },
    {
      "name": "逸夫楼",
      "room": [
        "401",
        "410"
      ]
    }
  ],
  [
    {
      "name": "",
      "room": [
        "104",
        "107",
        "108",
        "113",
        "115",
        "116",
        "A101",
        "A102",
        "A103",
        "A104",
        "A105",
        "A107",
        "A110",
        "A211",
        "A214",
        "A330",
        "A424",
        "A431",
        "A514",
        "A606",
        "A607",
        "A608",
        "A610",
        "A611",
        "A612",
        "A615",
        "A618",
        "B102",
        "B104",
        "B105",
        "B107",
        "N100",
        "N101",
        "N103",
        "N105",
        "N107",
        "N109",
        "N111",
        "N201",
        "N301",
        "N303",
        "N305",
        "N307",
        "N309",
        "N311",
        "S102",
        "S104",
        "S106",
        "S108",
        "S110",
        "S112",
        "S114",
        "S116",
        "S118",
        "S202",
        "S204",
        "S206",
        "S208",
        "S210",
        "S302",
        "S304",
        "S306",
        "S308",
        "S310",
        "S312",
        "S314"
      ]
    },
    {
      "name": "B",
      "room": [
        "101",
        "103",
        "104",
        "105",
        "106",
        "107",
        "108",
        "109",
        "201",
        "202",
        "203",
        "204",
        "205",
        "206",
        "207",
        "208",
        "209",
        "210",
        "211",
        "301",
        "302",
        "303",
        "304",
        "305",
        "306",
        "307",
        "308",
        "309",
        "310",
        "311",
        "312",
        "313",
        "401",
        "402",
        "403",
        "404",
        "405",
        "406",
        "407",
        "408",
        "410",
        "411",
        "412",
        "413",
        "502",
        "504",
        "519",
        "521",
        "523",
        "525"
      ]
    },
    {
      "name": "北山阶梯",
      "room": [
        "北山三阶梯",
        "北山一阶梯"
      ]
    },
    {
      "name": "北四阶",
      "room": [
        "北四阶"
      ]
    },
    {
      "name": "测试中心",
      "room": [
        "104",
        "105"
      ]
    },
    {
      "name": "车间",
      "room": [
        "1",
        "2"
      ]
    },
    {
      "name": "锻压楼",
      "room": [
        "101",
        "102",
        "103",
        "104",
        "105",
        "106",
        "107",
        "210"
      ]
    },
    {
      "name": "二教楼",
      "room": [
        "101",
        "102",
        "103",
        "104",
        "105",
        "106",
        "107",
        "108",
        "109",
        "110",
        "111",
        "113",
        "114",
        "115",
        "116",
        "117",
        "118",
        "119",
        "120",
        "121",
        "123",
        "201",
        "208",
        "210",
        "212",
        "216",
        "217",
        "219",
        "220",
        "221",
        "222",
        "223",
        "224",
        "225",
        "314",
        "319",
        "405"
      ]
    },
    {
      "name": "法学附",
      "room": [
        "101",
        "201",
        "202"
      ]
    },
    {
      "name": "封样室",
      "room": [
        "封样室"
      ]
    },
    {
      "name": "工科楼",
      "room": [
        "S101",
        "S102",
        "S110",
        "S110",
        "S111",
        "S201",
        "S202",
        "S203",
        "S204",
        "S206",
        "S207",
        "S208",
        "S210",
        "S211",
        "S212",
        "S213",
        "S215",
        "S218",
        "S219",
        "S220",
        "S302",
        "S308",
        "S310",
        "S402",
        "S403",
        "S409",
        "S420",
        "N504",
        "N601",
        "N602",
        "N603",
        "S502",
        "S503",
        "S513",
        "S514",
        "S602",
        "S609",
        "S610",
        "S611",
        "S612"
      ]
    },
    {
      "name": "工科楼阶梯",
      "room": [
        "工科楼阶梯"
      ]
    },
    {
      "name": "工科楼南楼",
      "room": [
        "103",
        "104",
        "105",
        "106",
        "107",
        "108",
        "109",
        "209",
        "214",
        "216",
        "217"
      ]
    },
    {
      "name": "焊接楼",
      "room": [
        "106",
        "101",
        "104",
        "105",
        "109",
        "111",
        "112",
        "113",
        "114",
        "115",
        "116",
        "117",
        "118",
        "119",
        "206",
        "208",
        "210",
        "211",
        "212",
        "213",
        "214",
        "215",
        "216",
        "303",
        "303",
        "305",
        "307",
        "310",
        "311",
        "311",
        "312",
        "313",
        "314",
        "316"
      ]
    },
    {
      "name": "化机楼",
      "room": [
        "101",
        "102",
        "103",
        "104",
        "105",
        "106",
        "107",
        "108",
        "109",
        "111",
        "112",
        "201",
        "204",
        "207",
        "209",
        "210",
        "212",
        "214",
        "215"
      ]
    },
    {
      "name": "环工实验室",
      "room": [
        "101",
        "105",
        "113",
        "115",
        "206",
        "213",
        "303",
        "310",
        "323"
      ]
    },
    {
      "name": "机械楼",
      "room": [
        "204",
        "115",
        "116",
        "215",
        "319",
        "320",
        "321",
        "502",
        "503",
        "505",
        "506",
        "507",
        "508",
        "511",
        "513",
        "515",
        "517",
        "601",
        "602",
        "603",
        "604",
        "605",
        "606",
        "608",
        "609",
        "610",
        "611",
        "612",
        "614",
        "615",
        "616",
        "617"
      ]
    },
    {
      "name": "机制大厅",
      "room": [
        "机制大厅"
      ]
    },
    {
      "name": "机制厅",
      "room": [
        "101",
        "102",
        "103",
        "104",
        "201",
        "204"
      ]
    },
    {
      "name": "经管楼",
      "room": [
        "202",
        "203",
        "401",
        "402",
        "601",
        "606",
        "617",
        "301",
        "302",
        "306",
        "406",
        "经管一阶梯"
      ]
    },
    {
      "name": "联建",
      "room": [
        "D201"
      ]
    },
    {
      "name": "模具大厅",
      "room": [
        "模具大厅"
      ]
    },
    {
      "name": "模具厅",
      "room": [
        "101",
        "102"
      ]
    },
    {
      "name": "三教宿",
      "room": [
        "202"
      ]
    },
    {
      "name": "生食工楼",
      "room": [
        "222"
      ]
    },
    {
      "name": "实验楼",
      "room": [
        "309"
      ]
    },
    {
      "name": "数学院报告厅",
      "room": [
        "数学院报告厅"
      ]
    },
    {
      "name": "四教区",
      "room": [
        "1101",
        "1103",
        "1104",
        "1105",
        "1106",
        "1107",
        "1108",
        "1109",
        "1112",
        "1201",
        "1203",
        "1204",
        "1205",
        "1206",
        "1207",
        "1208",
        "1209",
        "1210",
        "1304",
        "1305",
        "1306",
        "1307",
        "1308",
        "1309",
        "1310",
        "1313",
        "1401",
        "1403",
        "1404",
        "1405",
        "1406",
        "1407",
        "1408",
        "1409",
        "1410",
        "1413",
        "1503",
        "1504",
        "1505",
        "1506",
        "1507",
        "1508",
        "1509",
        "1510",
        "1512",
        "1601",
        "1613",
        "2201",
        "2202",
        "2203",
        "2204",
        "2205",
        "2301",
        "2302",
        "2303",
        "2304",
        "2305",
        "2401",
        "2402",
        "2403",
        "2404",
        "2405",
        "2501",
        "2502",
        "2503",
        "2504",
        "2505"
      ]
    },
    {
      "name": "四教区图书馆",
      "room": [
        "203",
        "303",
        "403"
      ]
    },
    {
      "name": "体育馆",
      "room": [
        "210"
      ]
    },
    {
      "name": "图书馆多媒体",
      "room": [
        "图书馆多媒体"
      ]
    },
    {
      "name": "图书馆文献检索室",
      "room": [
        "图书馆文献检索室"
      ]
    },
    {
      "name": "土木楼",
      "room": [
        "A426",
        "A518",
        "A601",
        "A602",
        "A603",
        "A604",
        "A605"
      ]
    },
    {
      "name": "外语楼",
      "room": [
        "105",
        "106",
        "316",
        "318",
        "319",
        "320",
        "321",
        "401",
        "501"
      ]
    },
    {
      "name": "文科楼",
      "room": [
        "102",
        "103",
        "106",
        "107",
        "201",
        "202",
        "203",
        "204",
        "205",
        "206",
        "207",
        "208",
        "301",
        "302",
        "303",
        "304",
        "305",
        "306",
        "307",
        "308",
        "401",
        "402",
        "403",
        "1楼",
        "1楼",
        "2楼",
        "405",
        "505"
      ]
    },
    {
      "name": "小二楼二楼",
      "room": [
        "小二楼二楼"
      ]
    },
    {
      "name": "小二楼一楼",
      "room": [
        "小二楼一楼"
      ]
    },
    {
      "name": "信息楼",
      "room": [
        "103",
        "104",
        "105",
        "106",
        "408",
        "409",
        "201",
        "301",
        "601",
        "603",
        "609"
      ]
    },
    {
      "name": "信息楼605",
      "room": [
        "1",
        "2"
      ]
    },
    {
      "name": "兴教楼",
      "room": [
        "A106",
        "B101",
        "B103",
        "B104",
        "B106",
        "B107",
        "B201",
        "B205",
        "B206",
        "B207",
        "B302",
        "B304",
        "B305",
        "B306",
        "B307",
        "B308",
        "B309",
        "B310",
        "B402",
        "B403",
        "B404",
        "B405",
        "B406",
        "B407",
        "B408",
        "B409",
        "C102",
        "C103",
        "C104",
        "C105",
        "C106",
        "C107",
        "C108",
        "C201",
        "C202",
        "C203",
        "C204",
        "C205",
        "C206",
        "C207",
        "C208",
        "C209",
        "C301",
        "C302",
        "C303",
        "C304",
        "C305",
        "C307",
        "C309"
      ]
    },
    {
      "name": "兴湘教学楼",
      "room": [
        "A101",
        "A102",
        "A103",
        "A104",
        "A105",
        "A106",
        "A201",
        "A202",
        "A203",
        "A204",
        "A205",
        "A206",
        "A207",
        "A208",
        "A301",
        "A302",
        "A303",
        "A304",
        "A305",
        "A306",
        "A307",
        "A308",
        "A309",
        "A401",
        "A402",
        "A410",
        "A415"
      ]
    },
    {
      "name": "兴湘学院三教",
      "room": [
        "101",
        "103",
        "104",
        "202",
        "203",
        "204",
        "205",
        "304",
        "305",
        "402",
        "403",
        "404",
        "405",
        "502"
      ]
    },
    {
      "name": "一教楼",
      "room": [
        "101",
        "102",
        "103",
        "104",
        "105",
        "106",
        "107",
        "108",
        "113",
        "114",
        "115",
        "116",
        "117",
        "118",
        "119",
        "201",
        "202",
        "203",
        "204",
        "205",
        "206",
        "207",
        "208",
        "212",
        "213",
        "214",
        "215",
        "216",
        "217",
        "218",
        "301",
        "302",
        "303",
        "304",
        "305",
        "306",
        "307",
        "308",
        "312",
        "313",
        "314",
        "315",
        "316",
        "317",
        "319",
        "401",
        "402",
        "414",
        "415",
        "416",
        "417",
        "418"
      ]
    },
    {
      "name": "逸夫楼",
      "room": [
        "102",
        "103",
        "108",
        "110",
        "111",
        "112",
        "201",
        "202",
        "203",
        "208",
        "209",
        "210",
        "211",
        "212",
        "301",
        "302",
        "303",
        "308",
        "309",
        "310",
        "311",
        "312",
        "401",
        "402",
        "403",
        "408",
        "409",
        "410",
        "411",
        "412",
        "503",
        "508",
        "509",
        "510",
        "511",
        "512",
        "逸夫楼二阶",
        "逸夫楼四阶"
      ]
    }
  ],
  [
    {
      "name": "",
      "room": [
        "104",
        "107",
        "108",
        "113",
        "115",
        "116",
        "A101",
        "A102",
        "A103",
        "A104",
        "A105",
        "A107",
        "A110",
        "A211",
        "A214",
        "A330",
        "A424",
        "A431",
        "A514",
        "A606",
        "A607",
        "A608",
        "A610",
        "A611",
        "A612",
        "A615",
        "A618",
        "B102",
        "B104",
        "B105",
        "B107",
        "N100",
        "N101",
        "N103",
        "N105",
        "N107",
        "N109",
        "N111",
        "N201",
        "N301",
        "N303",
        "N305",
        "N307",
        "N309",
        "N311",
        "S102",
        "S104",
        "S106",
        "S108",
        "S110",
        "S112",
        "S114",
        "S116",
        "S118",
        "S202",
        "S204",
        "S206",
        "S208",
        "S210",
        "S302",
        "S304",
        "S306",
        "S308",
        "S310",
        "S312",
        "S314"
      ]
    },
    {
      "name": "B",
      "room": [
        "101",
        "103",
        "104",
        "105",
        "106",
        "107",
        "108",
        "109",
        "201",
        "202",
        "203",
        "204",
        "205",
        "206",
        "207",
        "208",
        "209",
        "210",
        "211",
        "301",
        "302",
        "303",
        "304",
        "305",
        "306",
        "307",
        "308",
        "309",
        "310",
        "311",
        "312",
        "313",
        "401",
        "402",
        "403",
        "404",
        "405",
        "406",
        "407",
        "408",
        "410",
        "411",
        "412",
        "413",
        "502",
        "504",
        "519",
        "521",
        "523",
        "525"
      ]
    },
    {
      "name": "北山阶梯",
      "room": [
        "北山二阶梯",
        "北山一阶梯"
      ]
    },
    {
      "name": "北四阶",
      "room": [
        "北四阶"
      ]
    },
    {
      "name": "测试中心",
      "room": [
        "104",
        "105"
      ]
    },
    {
      "name": "车间",
      "room": [
        "1",
        "2"
      ]
    },
    {
      "name": "锻压楼",
      "room": [
        "101",
        "102",
        "103",
        "104",
        "105",
        "106",
        "107",
        "210"
      ]
    },
    {
      "name": "二教楼",
      "room": [
        "101",
        "102",
        "103",
        "104",
        "105",
        "106",
        "107",
        "108",
        "109",
        "110",
        "111",
        "113",
        "114",
        "115",
        "116",
        "117",
        "118",
        "119",
        "120",
        "121",
        "123",
        "201",
        "208",
        "210",
        "212",
        "216",
        "217",
        "219",
        "220",
        "221",
        "222",
        "223",
        "224",
        "225",
        "314",
        "319",
        "405"
      ]
    },
    {
      "name": "法学附",
      "room": [
        "101",
        "201",
        "202"
      ]
    },
    {
      "name": "封样室",
      "room": [
        "封样室"
      ]
    },
    {
      "name": "工科楼",
      "room": [
        "S101",
        "S102",
        "S110",
        "S110",
        "S111",
        "S201",
        "S202",
        "S203",
        "S204",
        "S206",
        "S207",
        "S208",
        "S210",
        "S211",
        "S212",
        "S213",
        "S215",
        "S218",
        "S219",
        "S220",
        "S302",
        "S308",
        "S310",
        "S402",
        "S403",
        "S409",
        "S420",
        "N504",
        "N601",
        "N602",
        "N603",
        "S502",
        "S503",
        "S513",
        "S514",
        "S602",
        "S609",
        "S610",
        "S611",
        "S612"
      ]
    },
    {
      "name": "工科楼阶梯",
      "room": [
        "工科楼阶梯"
      ]
    },
    {
      "name": "工科楼南楼",
      "room": [
        "103",
        "104",
        "105",
        "106",
        "107",
        "108",
        "109",
        "209",
        "214",
        "216",
        "217"
      ]
    },
    {
      "name": "焊接楼",
      "room": [
        "106",
        "101",
        "104",
        "105",
        "109",
        "111",
        "112",
        "113",
        "114",
        "115",
        "116",
        "117",
        "118",
        "119",
        "206",
        "208",
        "210",
        "211",
        "212",
        "213",
        "214",
        "215",
        "216",
        "303",
        "303",
        "305",
        "307",
        "310",
        "311",
        "311",
        "312",
        "313",
        "314",
        "316"
      ]
    },
    {
      "name": "化机楼",
      "room": [
        "101",
        "102",
        "103",
        "104",
        "105",
        "106",
        "107",
        "108",
        "109",
        "111",
        "112",
        "201",
        "204",
        "207",
        "209",
        "210",
        "212",
        "214",
        "215"
      ]
    },
    {
      "name": "环工实验室",
      "room": [
        "101",
        "105",
        "113",
        "115",
        "206",
        "213",
        "303",
        "310",
        "323"
      ]
    },
    {
      "name": "机械楼",
      "room": [
        "204",
        "115",
        "116",
        "215",
        "319",
        "320",
        "321",
        "502",
        "503",
        "505",
        "506",
        "507",
        "508",
        "511",
        "513",
        "515",
        "517",
        "601",
        "602",
        "603",
        "604",
        "605",
        "606",
        "608",
        "609",
        "610",
        "611",
        "612",
        "614",
        "615",
        "616",
        "617"
      ]
    },
    {
      "name": "机制大厅",
      "room": [
        "机制大厅"
      ]
    },
    {
      "name": "机制厅",
      "room": [
        "101",
        "102",
        "103",
        "104",
        "201",
        "204"
      ]
    },
    {
      "name": "计算中心",
      "room": [
        "B202"
      ]
    },
    {
      "name": "经管楼",
      "room": [
        "经管二阶梯",
        "202",
        "203",
        "401",
        "402",
        "601",
        "606",
        "617",
        "301",
        "302",
        "306",
        "406"
      ]
    },
    {
      "name": "联建",
      "room": [
        "D201"
      ]
    },
    {
      "name": "模具大厅",
      "room": [
        "模具大厅"
      ]
    },
    {
      "name": "模具厅",
      "room": [
        "101",
        "102"
      ]
    },
    {
      "name": "三教宿",
      "room": [
        "202"
      ]
    },
    {
      "name": "生食工楼",
      "room": [
        "222"
      ]
    },
    {
      "name": "实验楼",
      "room": [
        "309"
      ]
    },
    {
      "name": "数学院报告厅",
      "room": [
        "数学院报告厅"
      ]
    },
    {
      "name": "四教区",
      "room": [
        "1101",
        "1103",
        "1104",
        "1105",
        "1106",
        "1107",
        "1108",
        "1109",
        "1112",
        "1201",
        "1203",
        "1204",
        "1205",
        "1206",
        "1207",
        "1208",
        "1209",
        "1210",
        "1212",
        "1304",
        "1305",
        "1306",
        "1307",
        "1308",
        "1309",
        "1310",
        "1313",
        "1401",
        "1403",
        "1404",
        "1405",
        "1406",
        "1407",
        "1408",
        "1409",
        "1410",
        "1413",
        "1503",
        "1504",
        "1505",
        "1506",
        "1507",
        "1508",
        "1509",
        "1510",
        "1512",
        "1601",
        "1613",
        "2201",
        "2202",
        "2203",
        "2204",
        "2205",
        "2301",
        "2302",
        "2303",
        "2304",
        "2305",
        "2401",
        "2402",
        "2403",
        "2404",
        "2405",
        "2501",
        "2502",
        "2503",
        "2504",
        "2505"
      ]
    },
    {
      "name": "四教区图书馆",
      "room": [
        "203",
        "303",
        "403"
      ]
    },
    {
      "name": "体育馆",
      "room": [
        "210"
      ]
    },
    {
      "name": "图书馆多媒体",
      "room": [
        "图书馆多媒体"
      ]
    },
    {
      "name": "图书馆文献检索室",
      "room": [
        "图书馆文献检索室"
      ]
    },
    {
      "name": "土木楼",
      "room": [
        "A426",
        "A518",
        "A601",
        "A602",
        "A603",
        "A604",
        "A605"
      ]
    },
    {
      "name": "外语楼",
      "room": [
        "105",
        "106",
        "316",
        "318",
        "319",
        "320",
        "321",
        "401",
        "501"
      ]
    },
    {
      "name": "文科楼",
      "room": [
        "102",
        "103",
        "105",
        "106",
        "107",
        "201",
        "202",
        "203",
        "204",
        "205",
        "206",
        "207",
        "208",
        "301",
        "302",
        "303",
        "304",
        "305",
        "306",
        "307",
        "308",
        "401",
        "402",
        "403",
        "1楼",
        "1楼",
        "2楼",
        "405",
        "505"
      ]
    },
    {
      "name": "小二楼二楼",
      "room": [
        "小二楼二楼"
      ]
    },
    {
      "name": "小二楼一楼",
      "room": [
        "小二楼一楼"
      ]
    },
    {
      "name": "信息楼",
      "room": [
        "103",
        "104",
        "105",
        "106",
        "408",
        "409",
        "201",
        "301",
        "601",
        "603",
        "609"
      ]
    },
    {
      "name": "信息楼605",
      "room": [
        "1",
        "2"
      ]
    },
    {
      "name": "兴教楼",
      "room": [
        "A106",
        "B101",
        "B102",
        "B103",
        "B104",
        "B105",
        "B107",
        "B201",
        "B202",
        "B203",
        "B206",
        "B207",
        "B302",
        "B305",
        "B306",
        "B307",
        "B308",
        "B309",
        "B310",
        "B401",
        "B402",
        "B403",
        "B404",
        "B405",
        "B406",
        "B407",
        "B408",
        "B409",
        "C101",
        "C102",
        "C103",
        "C104",
        "C105",
        "C106",
        "C107",
        "C108",
        "C202",
        "C203",
        "C204",
        "C205",
        "C206",
        "C207",
        "C208",
        "C301",
        "C302",
        "C303",
        "C304",
        "C305",
        "C306",
        "C307",
        "C309"
      ]
    },
    {
      "name": "兴湘教学楼",
      "room": [
        "A101",
        "A102",
        "A103",
        "A104",
        "A105",
        "A106",
        "A201",
        "A202",
        "A203",
        "A204",
        "A205",
        "A206",
        "A207",
        "A208",
        "A301",
        "A302",
        "A303",
        "A304",
        "A305",
        "A306",
        "A307",
        "A308",
        "A309",
        "A401",
        "A402",
        "A410",
        "A415"
      ]
    },
    {
      "name": "兴湘学院三教",
      "room": [
        "101",
        "103",
        "104",
        "202",
        "204",
        "205",
        "302",
        "304",
        "305",
        "402",
        "403",
        "404",
        "405",
        "502"
      ]
    },
    {
      "name": "一教楼",
      "room": [
        "101",
        "102",
        "103",
        "104",
        "105",
        "106",
        "107",
        "108",
        "113",
        "114",
        "115",
        "116",
        "117",
        "119",
        "201",
        "202",
        "203",
        "204",
        "205",
        "206",
        "207",
        "208",
        "212",
        "213",
        "214",
        "215",
        "216",
        "217",
        "218",
        "219",
        "301",
        "302",
        "303",
        "304",
        "305",
        "306",
        "307",
        "308",
        "312",
        "313",
        "314",
        "315",
        "316",
        "317",
        "318",
        "319",
        "401",
        "402",
        "414",
        "415",
        "416",
        "417",
        "418"
      ]
    },
    {
      "name": "逸夫楼",
      "room": [
        "102",
        "103",
        "108",
        "109",
        "110",
        "111",
        "112",
        "201",
        "202",
        "203",
        "208",
        "209",
        "210",
        "211",
        "212",
        "301",
        "302",
        "303",
        "308",
        "309",
        "310",
        "311",
        "312",
        "402",
        "408",
        "409",
        "411",
        "412",
        "503",
        "508",
        "509",
        "510",
        "511",
        "512",
        "逸夫楼四阶"
      ]
    }
  ],
  [
    {
      "name": "",
      "room": [
        "104",
        "107",
        "108",
        "113",
        "115",
        "116",
        "A101",
        "A102",
        "A103",
        "A104",
        "A105",
        "A107",
        "A110",
        "A211",
        "A214",
        "A330",
        "A424",
        "A431",
        "A514",
        "A606",
        "A607",
        "A608",
        "A610",
        "A611",
        "A612",
        "A615",
        "A618",
        "B102",
        "B104",
        "B105",
        "B107",
        "N100",
        "N101",
        "N103",
        "N105",
        "N107",
        "N109",
        "N111",
        "N201",
        "N301",
        "N303",
        "N305",
        "N307",
        "N309",
        "N311",
        "S102",
        "S104",
        "S106",
        "S108",
        "S110",
        "S112",
        "S114",
        "S116",
        "S118",
        "S202",
        "S204",
        "S206",
        "S208",
        "S210",
        "S302",
        "S304",
        "S306",
        "S308",
        "S310",
        "S312",
        "S314"
      ]
    },
    {
      "name": "B",
      "room": [
        "101",
        "103",
        "104",
        "105",
        "106",
        "107",
        "108",
        "109",
        "201",
        "202",
        "203",
        "204",
        "205",
        "206",
        "207",
        "208",
        "209",
        "210",
        "211",
        "301",
        "302",
        "303",
        "304",
        "305",
        "306",
        "307",
        "308",
        "309",
        "310",
        "311",
        "312",
        "313",
        "401",
        "402",
        "403",
        "404",
        "405",
        "406",
        "407",
        "408",
        "410",
        "411",
        "412",
        "413",
        "502",
        "504",
        "519",
        "521",
        "523",
        "525"
      ]
    },
    {
      "name": "北四阶",
      "room": [
        "北四阶"
      ]
    },
    {
      "name": "测试中心",
      "room": [
        "104",
        "105"
      ]
    },
    {
      "name": "车间",
      "room": [
        "1",
        "2"
      ]
    },
    {
      "name": "锻压楼",
      "room": [
        "101",
        "102",
        "103",
        "104",
        "105",
        "106",
        "107",
        "210"
      ]
    },
    {
      "name": "二教楼",
      "room": [
        "101",
        "102",
        "103",
        "104",
        "105",
        "106",
        "107",
        "108",
        "109",
        "110",
        "111",
        "113",
        "114",
        "115",
        "116",
        "117",
        "118",
        "119",
        "120",
        "121",
        "123",
        "201",
        "208",
        "210",
        "212",
        "216",
        "217",
        "219",
        "220",
        "221",
        "222",
        "223",
        "224",
        "225",
        "314",
        "319",
        "405"
      ]
    },
    {
      "name": "法学附",
      "room": [
        "102"
      ]
    },
    {
      "name": "封样室",
      "room": [
        "封样室"
      ]
    },
    {
      "name": "工科楼",
      "room": [
        "S101",
        "S102",
        "S110",
        "S110",
        "S111",
        "S201",
        "S202",
        "S203",
        "S204",
        "S206",
        "S207",
        "S208",
        "S210",
        "S211",
        "S212",
        "S213",
        "S215",
        "S218",
        "S219",
        "S220",
        "S302",
        "S308",
        "S310",
        "S402",
        "S403",
        "S409",
        "S420",
        "N504",
        "N601",
        "N602",
        "N603",
        "S502",
        "S503",
        "S513",
        "S514",
        "S602",
        "S609",
        "S610",
        "S611",
        "S612"
      ]
    },
    {
      "name": "工科楼阶梯",
      "room": [
        "工科楼阶梯"
      ]
    },
    {
      "name": "工科楼南楼",
      "room": [
        "103",
        "104",
        "105",
        "106",
        "107",
        "108",
        "109",
        "209",
        "214",
        "216",
        "217"
      ]
    },
    {
      "name": "焊接楼",
      "room": [
        "106",
        "101",
        "104",
        "105",
        "109",
        "111",
        "112",
        "113",
        "114",
        "115",
        "116",
        "117",
        "118",
        "119",
        "206",
        "208",
        "210",
        "211",
        "212",
        "213",
        "214",
        "215",
        "216",
        "303",
        "303",
        "305",
        "307",
        "310",
        "311",
        "311",
        "312",
        "313",
        "314",
        "316"
      ]
    },
    {
      "name": "化机楼",
      "room": [
        "101",
        "102",
        "103",
        "104",
        "105",
        "106",
        "107",
        "108",
        "109",
        "111",
        "112",
        "201",
        "204",
        "207",
        "209",
        "210",
        "212",
        "214",
        "215"
      ]
    },
    {
      "name": "环工实验室",
      "room": [
        "101",
        "105",
        "113",
        "115",
        "206",
        "213",
        "303",
        "310",
        "323"
      ]
    },
    {
      "name": "机械楼",
      "room": [
        "204",
        "115",
        "116",
        "215",
        "319",
        "320",
        "321",
        "502",
        "503",
        "505",
        "506",
        "507",
        "508",
        "511",
        "513",
        "515",
        "517",
        "601",
        "602",
        "603",
        "604",
        "605",
        "606",
        "608",
        "609",
        "610",
        "611",
        "612",
        "614",
        "615",
        "616",
        "617"
      ]
    },
    {
      "name": "机制大厅",
      "room": [
        "机制大厅"
      ]
    },
    {
      "name": "机制厅",
      "room": [
        "101",
        "102",
        "103",
        "104",
        "201",
        "204"
      ]
    },
    {
      "name": "计算中心",
      "room": [
        "B202"
      ]
    },
    {
      "name": "经管楼",
      "room": [
        "401",
        "606",
        "617",
        "301",
        "302",
        "306",
        "406"
      ]
    },
    {
      "name": "联建",
      "room": [
        "D201"
      ]
    },
    {
      "name": "模具大厅",
      "room": [
        "模具大厅"
      ]
    },
    {
      "name": "模具厅",
      "room": [
        "101",
        "102"
      ]
    },
    {
      "name": "南山阶梯",
      "room": [
        "南山四阶梯"
      ]
    },
    {
      "name": "三教宿",
      "room": [
        "202"
      ]
    },
    {
      "name": "生食工楼",
      "room": [
        "222"
      ]
    },
    {
      "name": "实验楼",
      "room": [
        "309"
      ]
    },
    {
      "name": "数学院报告厅",
      "room": [
        "数学院报告厅"
      ]
    },
    {
      "name": "四教区",
      "room": [
        "1101",
        "1103",
        "1104",
        "1105",
        "1106",
        "1107",
        "1108",
        "1109",
        "1112",
        "1203",
        "1204",
        "1205",
        "1206",
        "1207",
        "1208",
        "1209",
        "1210",
        "1304",
        "1305",
        "1306",
        "1307",
        "1308",
        "1309",
        "1310",
        "1403",
        "1404",
        "1405",
        "1406",
        "1407",
        "1408",
        "1409",
        "1410",
        "1413",
        "1503",
        "1504",
        "1505",
        "1506",
        "1507",
        "1508",
        "1509",
        "1510",
        "1512",
        "1601",
        "1613",
        "2201",
        "2202",
        "2203",
        "2204",
        "2205",
        "2301",
        "2302",
        "2303",
        "2304",
        "2305",
        "2401",
        "2402",
        "2403",
        "2404",
        "2405",
        "2501",
        "2502",
        "2503",
        "2504",
        "2505"
      ]
    },
    {
      "name": "四教区图书馆",
      "room": [
        "203",
        "303",
        "403"
      ]
    },
    {
      "name": "体育馆",
      "room": [
        "210"
      ]
    },
    {
      "name": "图书馆多媒体",
      "room": [
        "图书馆多媒体"
      ]
    },
    {
      "name": "图书馆文献检索室",
      "room": [
        "图书馆文献检索室"
      ]
    },
    {
      "name": "土木楼",
      "room": [
        "A426",
        "A518",
        "A601",
        "A602",
        "A605"
      ]
    },
    {
      "name": "外语楼",
      "room": [
        "105",
        "106",
        "218",
        "219",
        "220",
        "316",
        "318",
        "320",
        "321",
        "401"
      ]
    },
    {
      "name": "文科楼",
      "room": [
        "102",
        "103",
        "104",
        "105",
        "106",
        "107",
        "201",
        "202",
        "203",
        "204",
        "205",
        "206",
        "207",
        "208",
        "301",
        "302",
        "303",
        "304",
        "305",
        "306",
        "307",
        "308",
        "401",
        "402",
        "403",
        "1楼",
        "1楼",
        "2楼",
        "405",
        "505"
      ]
    },
    {
      "name": "小二楼二楼",
      "room": [
        "小二楼二楼"
      ]
    },
    {
      "name": "小二楼一楼",
      "room": [
        "小二楼一楼"
      ]
    },
    {
      "name": "信息楼",
      "room": [
        "103",
        "104",
        "105",
        "106",
        "408",
        "409",
        "201",
        "301",
        "601",
        "603",
        "609"
      ]
    },
    {
      "name": "信息楼605",
      "room": [
        "1",
        "2"
      ]
    },
    {
      "name": "兴教楼",
      "room": [
        "B101",
        "B102",
        "B103",
        "B104",
        "B107",
        "B201",
        "B202",
        "B203",
        "B204",
        "B205",
        "B207",
        "B301",
        "B302",
        "B304",
        "B305",
        "B306",
        "B307",
        "B308",
        "B309",
        "B401",
        "B402",
        "B403",
        "B404",
        "B405",
        "B406",
        "B407",
        "B408",
        "B409",
        "C203",
        "C204",
        "C206",
        "C305",
        "C308"
      ]
    },
    {
      "name": "兴湘教学楼",
      "room": [
        "A101",
        "A102",
        "A103",
        "A104",
        "A105",
        "A106",
        "A201",
        "A202",
        "A203",
        "A204",
        "A205",
        "A206",
        "A207",
        "A208",
        "A301",
        "A302",
        "A303",
        "A304",
        "A305",
        "A306",
        "A307",
        "A308",
        "A309",
        "A401",
        "A402",
        "A410",
        "A415"
      ]
    },
    {
      "name": "兴湘学院三教",
      "room": [
        "101",
        "102",
        "103",
        "104",
        "202",
        "203",
        "204",
        "205",
        "302",
        "304",
        "305",
        "403",
        "404",
        "501"
      ]
    },
    {
      "name": "一教楼",
      "room": [
        "102",
        "103",
        "105",
        "107",
        "108",
        "115",
        "116",
        "117",
        "201",
        "202",
        "203",
        "204",
        "205",
        "206",
        "207",
        "208",
        "212",
        "213",
        "214",
        "215",
        "216",
        "217",
        "301",
        "302",
        "303",
        "304",
        "305",
        "306",
        "307",
        "308",
        "312",
        "313",
        "314",
        "315",
        "316",
        "317",
        "401",
        "402",
        "414",
        "415",
        "416",
        "417",
        "418"
      ]
    },
    {
      "name": "逸夫楼",
      "room": [
        "212",
        "411",
        "503",
        "510",
        "511",
        "512"
      ]
    }
  ]
]